pyxdc/__init__.py
pyxdc/account.py
pyxdc/config.py
pyxdc/exceptions.py
pyxdc/log.py
pyxdc/rpc.py
pyxdc/signature.py
pyxdc/transaction.py
pyxdc/utils.py
pyxdc/wallet.py
pyxdc/libs/__init__.py
pyxdc/libs/base58.py
pyxdc/libs/ed25519.py
pyxdc/libs/segwit.py
pyxdc-0.2.0.dist-info/LICENSE
pyxdc-0.2.0.dist-info/METADATA
pyxdc-0.2.0.dist-info/WHEEL
pyxdc-0.2.0.dist-info/top_level.txt
pyxdc-0.2.0.dist-info/RECORD
