Metadata-Version: 2.1
Name: pyxdc
Version: 0.2.0
Summary: Python library with tools for XinFin blockchain.
Home-page: https://github.com/meherett/pyxdc
Author: Meheret Tesfaye Batu
Author-email: meherett.batu@gmail.com
License: MIT
Keywords: xinfin,wallet,protocol,blockchain
Platform: UNKNOWN
Classifier: Development Status :: 5 - Production/Stable
Classifier: License :: OSI Approved :: MIT License
Classifier: Programming Language :: Python :: 3.6
Classifier: Programming Language :: Python :: 3.7
Classifier: Programming Language :: Python :: 3.8
Classifier: Programming Language :: Python :: 3.9
Classifier: Topic :: Software Development :: Libraries :: Python Modules
Requires-Python: >=3.6,<4
License-File: LICENSE
Requires-Dist: ecdsa (<1,>=0.13)
Requires-Dist: mnemonic (<1,>=0.19)
Requires-Dist: pysha3 (<2,>=1.0.2)
Requires-Dist: ed25519 (<2,>=1.5)
Requires-Dist: base58 (<3,>=2.0.1)
Requires-Dist: requests (<3,>=2.25.0)
Requires-Dist: hdwallet (<3,>=2.2.1)
Requires-Dist: rlp (<5,>=4.0.0)
Requires-Dist: web3 (<7,>=6.11.4)
Provides-Extra: docs
Requires-Dist: sphinx (<4,>=3.5.4) ; extra == 'docs'
Requires-Dist: sphinx-rtd-theme (<1,>=0.5.2) ; extra == 'docs'
Provides-Extra: tests
Requires-Dist: pytest (<8,>=7.4.3) ; extra == 'tests'
Requires-Dist: pytest-cov (<5,>=4.1.0) ; extra == 'tests'
